README
setup.py
oops_dictconfig/__init__.py
oops_dictconfig/configglue_options.py
oops_dictconfig/dictconfig.py
oops_dictconfig.egg-info/PKG-INFO
oops_dictconfig.egg-info/SOURCES.txt
oops_dictconfig.egg-info/dependency_links.txt
oops_dictconfig.egg-info/requires.txt
oops_dictconfig.egg-info/top_level.txt
oops_dictconfig/tests/__init__.py
oops_dictconfig/tests/test_configglue_options.py
oops_dictconfig/tests/test_dictconfig.py