Metadata-Version: 1.1
Name: oops-dictconfig
Version: 0.0.6
Summary: Create an oops Config from a definition encoded as a dict
Home-page: http://launchpad.net/python-oops-dictconfig
Author: Launchpad developers
Author-email: launchpad-devs@lists.launchpad.net
License: LGPLv3
Download-URL: https://launchpad.net/python-oops-dictconfig/+download
Platform: UNKNOWN
